examples/__init__.py
examples/storage/__init__.py
examples/storage/example.py
prefect_lakefs/__init__.py
prefect_lakefs/_version.py
prefect_lakefs/branches.py
prefect_lakefs/commits.py
prefect_lakefs/credentials.py
prefect_lakefs/internal.py
prefect_lakefs/objects.py
prefect_lakefs/refs.py
prefect_lakefs/storage.py
prefect_lakefs/tasks.py
prefect_lakefs-0.4.0.dist-info/LICENSE
prefect_lakefs-0.4.0.dist-info/METADATA
prefect_lakefs-0.4.0.dist-info/WHEEL
prefect_lakefs-0.4.0.dist-info/entry_points.txt
prefect_lakefs-0.4.0.dist-info/top_level.txt
prefect_lakefs-0.4.0.dist-info/RECORD
